canseer/README.md
canseer/cancer_plotting.py
canseer/data/ods_data/geographic_etr.csv
canseer/data/ons_shapefile/Integrated_Care_Boards_April_2023_EN_BFC_1659257819249669363/ICB_APR_2023_EN_BFC.cpg
canseer/data/ons_shapefile/Integrated_Care_Boards_April_2023_EN_BFC_1659257819249669363/ICB_APR_2023_EN_BFC.dbf
canseer/data/ons_shapefile/Integrated_Care_Boards_April_2023_EN_BFC_1659257819249669363/ICB_APR_2023_EN_BFC.prj
canseer/data/ons_shapefile/Integrated_Care_Boards_April_2023_EN_BFC_1659257819249669363/ICB_APR_2023_EN_BFC.shp
canseer/data/ons_shapefile/Integrated_Care_Boards_April_2023_EN_BFC_1659257819249669363/ICB_APR_2023_EN_BFC.shp.xml
canseer/data/ons_shapefile/Integrated_Care_Boards_April_2023_EN_BFC_1659257819249669363/ICB_APR_2023_EN_BFC.shx
canseer/data/ons_shapefile/Sub_ICB_Locations_to_Integrated_Care_Boards_to_NHS_England_(Region)_(July_2022)_Lookup_in_England.csv
canseer/data/ons_shapefile/Sub_Integrated_Care_Board_Locations_April_2023_EN_BGC_-4649276714948222786/SICBL_APR_2023_EN_BGC.cpg
canseer/data/ons_shapefile/Sub_Integrated_Care_Board_Locations_April_2023_EN_BGC_-4649276714948222786/SICBL_APR_2023_EN_BGC.dbf
canseer/data/ons_shapefile/Sub_Integrated_Care_Board_Locations_April_2023_EN_BGC_-4649276714948222786/SICBL_APR_2023_EN_BGC.prj
canseer/data/ons_shapefile/Sub_Integrated_Care_Board_Locations_April_2023_EN_BGC_-4649276714948222786/SICBL_APR_2023_EN_BGC.shp
canseer/data/ons_shapefile/Sub_Integrated_Care_Board_Locations_April_2023_EN_BGC_-4649276714948222786/SICBL_APR_2023_EN_BGC.shp.xml
canseer/data/ons_shapefile/Sub_Integrated_Care_Board_Locations_April_2023_EN_BGC_-4649276714948222786/SICBL_APR_2023_EN_BGC.shx
canseer/data_wrangling.py
canseer/version.py
canseer-0.1.0.dist-info/LICENSE
canseer-0.1.0.dist-info/METADATA
canseer-0.1.0.dist-info/WHEEL
canseer-0.1.0.dist-info/RECORD
